withingpy/__init__.py
withingpy/cli.py
withingpy/models.py
withingpy/py.typed
withingpy/values.py
withingpy/withings_api_client.py
withingpy-1.0.10.dist-info/METADATA
withingpy-1.0.10.dist-info/WHEEL
withingpy-1.0.10.dist-info/entry_points.txt
withingpy-1.0.10.dist-info/licenses/LICENSE
withingpy-1.0.10.dist-info/RECORD
