Metadata-Version: 2.4
Name: withingpy
Version: 1.0.10
Summary: Withings Public API Integration
Project-URL: Homepage, https://iandday.github.io/withingpy/
Project-URL: Documentation, https://iandday.github.io/withingpy/
Project-URL: Repository, https://github.com/iandday/withingpy
Project-URL: Issues, https://github.com/iandday/withingpy/issues
Project-URL: Changelog, https://github.com/iandday/withingpy/master/CHANGELOG.md
Author-email: Ian Day <ian@ianday.me>
License: GPL-3.0-or-later
License-File: LICENSE
Classifier: Development Status :: 4 - Beta
Classifier: Intended Audience :: Developers
Classifier: Natural Language :: English
Classifier: Operating System :: OS Independent
Classifier: Programming Language :: Python :: 3
Classifier: Programming Language :: Python :: 3.12
Classifier: Programming Language :: Python :: 3.13
Requires-Python: >=3.12
Requires-Dist: pydantic>=2.11.5
Requires-Dist: requests>=2.32.3
Requires-Dist: typer>=0.15.4
